hangman_game/__init__.py
hangman_game/__main__.py
hangman_game/database.py
hangman_game/easy_level.py
hangman_game/engine.py
hangman_game/hard_level.py
hangman_game/helpers.py
hangman_game/inquirer.py
hangman_game/renderer.py
hangman_game/assets/banner.txt
hangman_game-1.0.6.dist-info/LICENSE
hangman_game-1.0.6.dist-info/METADATA
hangman_game-1.0.6.dist-info/WHEEL
hangman_game-1.0.6.dist-info/entry_points.txt
hangman_game-1.0.6.dist-info/top_level.txt
hangman_game-1.0.6.dist-info/RECORD
