Metadata-Version: 2.1
Name: hangman-game
Version: 1.0.6
Summary: A CLI game built with Python
Home-page: https://github.com/chrisenytc/hangman
Author: Christopher Enytc
Author-email: chris@enytc.com
License: UNKNOWN
Platform: UNKNOWN
Classifier: Programming Language :: Python :: 3
Classifier: License :: OSI Approved :: MIT License
Classifier: Operating System :: OS Independent
